odoo/addons/stock_picking_inter_warehouse/README.rst
odoo/addons/stock_picking_inter_warehouse/__init__.py
odoo/addons/stock_picking_inter_warehouse/__manifest__.py
odoo/addons/stock_picking_inter_warehouse/hooks.py
odoo/addons/stock_picking_inter_warehouse/demo/res_config_settings_demo.xml
odoo/addons/stock_picking_inter_warehouse/demo/stock_warehouse_demo.xml
odoo/addons/stock_picking_inter_warehouse/i18n/it.po
odoo/addons/stock_picking_inter_warehouse/i18n/stock_picking_inter_warehouse.pot
odoo/addons/stock_picking_inter_warehouse/migrations/14.0.1.1.0/post-migrate.py
odoo/addons/stock_picking_inter_warehouse/models/__init__.py
odoo/addons/stock_picking_inter_warehouse/models/res_company.py
odoo/addons/stock_picking_inter_warehouse/models/res_partner.py
odoo/addons/stock_picking_inter_warehouse/models/stock_location.py
odoo/addons/stock_picking_inter_warehouse/models/stock_move.py
odoo/addons/stock_picking_inter_warehouse/models/stock_picking.py
odoo/addons/stock_picking_inter_warehouse/models/stock_picking_type.py
odoo/addons/stock_picking_inter_warehouse/models/stock_rule.py
odoo/addons/stock_picking_inter_warehouse/models/stock_warehouse.py
odoo/addons/stock_picking_inter_warehouse/readme/CONFIGURE.rst
odoo/addons/stock_picking_inter_warehouse/readme/CONTRIBUTORS.rst
odoo/addons/stock_picking_inter_warehouse/readme/DESCRIPTION.rst
odoo/addons/stock_picking_inter_warehouse/readme/USAGE.rst
odoo/addons/stock_picking_inter_warehouse/static/description/icon.png
odoo/addons/stock_picking_inter_warehouse/static/description/index.html
odoo/addons/stock_picking_inter_warehouse/tests/__init__.py
odoo/addons/stock_picking_inter_warehouse/tests/test_stock_picking_inter_warehouse.py
odoo/addons/stock_picking_inter_warehouse/views/stock_picking_type_views.xml
odoo/addons/stock_picking_inter_warehouse/views/stock_picking_views.xml
odoo/addons/stock_picking_inter_warehouse/views/stock_warehouse_views.xml
odoo14_addon_stock_picking_inter_warehouse-14.0.1.2.2.dist-info/METADATA
odoo14_addon_stock_picking_inter_warehouse-14.0.1.2.2.dist-info/WHEEL
odoo14_addon_stock_picking_inter_warehouse-14.0.1.2.2.dist-info/top_level.txt
odoo14_addon_stock_picking_inter_warehouse-14.0.1.2.2.dist-info/RECORD
