Metadata-Version: 2.1
Name: odoo14-addon-stock-picking-inter-warehouse
Version: 14.0.1.2.2
Summary: Stock Picking Inter Warehouse
Home-page: https://github.com/OCA/stock-logistics-workflow
Author: PyTech SRL, Ooops404, Odoo Community Association (OCA)
Author-email: support@odoo-community.org
License: AGPL-3
Platform: UNKNOWN
Classifier: Programming Language :: Python
Classifier: Framework :: Odoo
Classifier: Framework :: Odoo :: 14.0
Classifier: License :: OSI Approved :: GNU Affero General Public License v3
Requires-Python: >=3.6
Requires-Dist: odoo <14.1dev,>=14.0a
